jval/__init__.py
jval/__main__.py
jval/errors.py
jval/validation.py
jval-1.0.6.dist-info/entry_points.txt
jval-1.0.6.dist-info/LICENSE
jval-1.0.6.dist-info/METADATA
jval-1.0.6.dist-info/WHEEL
jval-1.0.6.dist-info/RECORD
