Metadata-Version: 2.3
Name: jval
Version: 1.0.6
Summary: Structural and type validation of JSON objects
License: GPL-2.0-only
Author: Julio Cabria
Author-email: juliocabria@tutanota.com
Requires-Python: >=3.9,<4.0
Classifier: License :: OSI Approved :: GNU General Public License v2 (GPLv2)
Classifier: Programming Language :: Python :: 3
Classifier: Programming Language :: Python :: 3.9
Classifier: Programming Language :: Python :: 3.10
Classifier: Programming Language :: Python :: 3.11
Classifier: Programming Language :: Python :: 3.12
Classifier: Programming Language :: Python :: 3.13
Project-URL: Homepage, https://github.com/Julynx/jval
